{
  "classification": "LEGITIMATE_BUG",
  "confidence": "HIGH",
  "reasoning": "The screenshot clearly shows that a script tag XSS payload was accepted and saved in the Measurement ID field without any input validation or sanitization. Since this tracking ID gets injected into page HTML (as noted in the observations), this represents a real XSS security vulnerability.",
  "evidence_summary": "Screenshot shows the Google Analytics 4 connector configuration with '<script>alert('XSS')</script>' visible in the Measurement ID text field, with a green checkmark indicating the connector is connected/saved. No error message or validation rejection occurred.",
  "scenario_id": "Evoq.GoogleAnalyticsConnector::Universal Analytics & GA4 Support::Special characters and XSS input",
  "timestamp": "2026-02-27T18:23:32.220753"
}